{
  "required": true,
  "minVersion": "0.8",
  "package": "net.blancworks.figura.mixin",
  "compatibilityLevel": "JAVA_8",
  "mixins": [
  ],
  "client": [
    "PlayerEntityModelMixin",
    "PlayerEntityRendererMixin",
    "ClientLoginNetworkHandlerMixin",
    "ModelPartMixin",
    "ElytraFeatureRendererMixin",
    "GameMenuScreenMixin",
    "MatrixStackMixin",
    "MixinDebugHud",
    "ArmorFeatureRendererMixin",
    "LivingEntityRendererMixin",
    "WorldRendererMixin",
    "ElytraEntityModelMixin",
    "HeldItemFeatureRendererMixin"
  ],
  "injectors": {
    "defaultRequire": 1
  }
}
